{
  "activeSpecies": [
    {
      "stamina": -70.3397,
      "age": 1440,
      "reproductiveUrge": 14.160229,
      "hunger": 5.9000044,
      "thirst": 13.610016,
      "speciesName": "",
      "xPos": 270.81982,
      "yPos": 131.42068,
      "currentState": 0,
      "genes": "4:500:1:99:25",
      "speed": 4,
      "eyeSght": 500,
      "gender": 1,
      "maxLife": 99,
      "reproductiveAge": 25
    },
    {
      "stamina": -69.97969,
      "age": 1440,
      "reproductiveUrge": 3.1899974,
      "hunger": 15.960043,
      "thirst": 32.22008,
      "speciesName": "",
      "xPos": 597.47327,
      "yPos": 29.685978,
      "currentState": 0,
      "genes": "4:500:0:100:25",
      "speed": 4,
      "eyeSght": 500,
      "gender": 0,
      "maxLife": 100,
      "reproductiveAge": 25
    },
    {
      "stamina": -69.97968,
      "age": 1440,
      "reproductiveUrge": 14.160229,
      "hunger": 10.670023,
      "thirst": 0.3,
      "speciesName": "",
      "xPos": 270.2288,
      "yPos": 188.22406,
      "currentState": 0,
      "genes": "4:500:1:100:25",
      "speed": 4,
      "eyeSght": 500,
      "gender": 1,
      "maxLife": 100,
      "reproductiveAge": 25
    },
    {
      "stamina": -68.71962,
      "age": 1440,
      "reproductiveUrge": 0.5499998,
      "hunger": 1.3599998,
      "thirst": 0.8000001,
      "speciesName": "",
      "xPos": 576.56934,
      "yPos": 47.12533,
      "currentState": 0,
      "genes": "5:500:0:99:24",
      "speed": 5,
      "eyeSght": 500,
      "gender": 0,
      "maxLife": 99,
      "reproductiveAge": 24
    },
    {
      "stamina": -70.57972,
      "age": 1440,
      "reproductiveUrge": 14.170229,
      "hunger": 6.850008,
      "thirst": 14.510019,
      "speciesName": "",
      "xPos": 679.42633,
      "yPos": 66.714096,
      "currentState": 0,
      "genes": "4:499:1:100:24",
      "speed": 4,
      "eyeSght": 499,
      "gender": 1,
      "maxLife": 100,
      "reproductiveAge": 24
    },
    {
      "stamina": -69.91968,
      "age": 1440,
      "reproductiveUrge": 14.160229,
      "hunger": 4.449999,
      "thirst": 10.010002,
      "speciesName": "",
      "xPos": 610.78314,
      "yPos": 32.58635,
      "currentState": 0,
      "genes": "5:500:1:100:25",
      "speed": 5,
      "eyeSght": 500,
      "gender": 1,
      "maxLife": 100,
      "reproductiveAge": 25
    },
    {
      "stamina": -68.239586,
      "age": 1440,
      "reproductiveUrge": 0.7099996,
      "hunger": 0.56000006,
      "thirst": 1.1000001,
      "speciesName": "",
      "xPos": 145.38835,
      "yPos": 49.87705,
      "currentState": 0,
      "genes": "5:500:0:100:24",
      "speed": 5,
      "eyeSght": 500,
      "gender": 0,
      "maxLife": 100,
      "reproductiveAge": 24
    },
    {
      "stamina": -70.03969,
      "age": 1440,
      "reproductiveUrge": 3.4099972,
      "hunger": 8.500014,
      "thirst": 17.710032,
      "speciesName": "",
      "xPos": 596.6625,
      "yPos": 28.952898,
      "currentState": 0,
      "genes": "4:500:0:100:25",
      "speed": 4,
      "eyeSght": 500,
      "gender": 0,
      "maxLife": 100,
      "reproductiveAge": 25
    },
    {
      "stamina": -69.919685,
      "age": 1440,
      "reproductiveUrge": 3.3999972,
      "hunger": 5.8600044,
      "thirst": 8.799997,
      "speciesName": "",
      "xPos": 587.3739,
      "yPos": 28.087013,
      "currentState": 0,
      "genes": "4:500:0:100:24",
      "speed": 4,
      "eyeSght": 500,
      "gender": 0,
      "maxLife": 100,
      "reproductiveAge": 24
    },
    {
      "stamina": -57.169422,
      "age": 1173,
      "reproductiveUrge": 11.500168,
      "hunger": 8.060013,
      "thirst": 5.499997,
      "speciesName": "",
      "xPos": 607.7946,
      "yPos": 32.649498,
      "currentState": 0,
      "genes": "4:500:1:100:24",
      "speed": 4,
      "eyeSght": 500,
      "gender": 1,
      "maxLife": 100,
      "reproductiveAge": 24
    },
    {
      "stamina": -42.849636,
      "age": 889,
      "reproductiveUrge": 8.670103,
      "hunger": 6.6100073,
      "thirst": 3.0999992,
      "speciesName": "",
      "xPos": 687.22284,
      "yPos": 68.385414,
      "currentState": 0,
      "genes": "4:500:1:99:23",
      "speed": 4,
      "eyeSght": 500,
      "gender": 1,
      "maxLife": 99,
      "reproductiveAge": 23
    },
    {
      "stamina": -39.36969,
      "age": 823,
      "reproductiveUrge": 0.16,
      "hunger": 2.0099993,
      "thirst": 5.719997,
      "speciesName": "",
      "xPos": 265.60696,
      "yPos": 137.69514,
      "currentState": 0,
      "genes": "3:500:0:99:22",
      "speed": 3,
      "eyeSght": 500,
      "gender": 0,
      "maxLife": 99,
      "reproductiveAge": 22
    },
    {
      "stamina": -32.54979,
      "age": 683,
      "reproductiveUrge": 1.6399988,
      "hunger": 0.45000005,
      "thirst": 3.7099986,
      "speciesName": "",
      "xPos": 166.31952,
      "yPos": 384.71103,
      "currentState": 0,
      "genes": "4:499:0:98:24",
      "speed": 4,
      "eyeSght": 499,
      "gender": 0,
      "maxLife": 98,
      "reproductiveAge": 24
    },
    {
      "stamina": -27.08987,
      "age": 581,
      "reproductiveUrge": 5.580033,
      "hunger": 5.760004,
      "thirst": 5.9999967,
      "speciesName": "",
      "xPos": 281.1794,
      "yPos": 330.7643,
      "currentState": 0,
      "genes": "4:500:1:98:24",
      "speed": 4,
      "eyeSght": 500,
      "gender": 1,
      "maxLife": 98,
      "reproductiveAge": 24
    },
    {
      "stamina": -26.169884,
      "age": 559,
      "reproductiveUrge": 1.8799986,
      "hunger": 3.1499982,
      "thirst": 7.9099946,
      "speciesName": "",
      "xPos": 606.2707,
      "yPos": 30.262804,
      "currentState": 0,
      "genes": "4:500:0:98:23",
      "speed": 4,
      "eyeSght": 500,
      "gender": 0,
      "maxLife": 98,
      "reproductiveAge": 23
    },
    {
      "stamina": -25.559895,
      "age": 542,
      "reproductiveUrge": 0.32999995,
      "hunger": 1.6099995,
      "thirst": 3.8199985,
      "speciesName": "",
      "xPos": 283.69067,
      "yPos": 335.9768,
      "currentState": 0,
      "genes": "3:499:0:99:23",
      "speed": 3,
      "eyeSght": 499,
      "gender": 0,
      "maxLife": 99,
      "reproductiveAge": 23
    },
    {
      "stamina": -23.789923,
      "age": 503,
      "reproductiveUrge": 4.8200154,
      "hunger": 8.260014,
      "thirst": 13.100014,
      "speciesName": "",
      "xPos": 610.66156,
      "yPos": 32.598846,
      "currentState": 0,
      "genes": "3:499:0:99:22",
      "speed": 3,
      "eyeSght": 499,
      "gender": 0,
      "maxLife": 99,
      "reproductiveAge": 22
    },
    {
      "stamina": -20.599972,
      "age": 438,
      "reproductiveUrge": 4.1600003,
      "hunger": 6.850008,
      "thirst": 20.11004,
      "speciesName": "",
      "xPos": 272.42288,
      "yPos": 130.61163,
      "currentState": 0,
      "genes": "2:498:0:99:23",
      "speed": 2,
      "eyeSght": 498,
      "gender": 0,
      "maxLife": 99,
      "reproductiveAge": 23
    },
    {
      "stamina": -17.600018,
      "age": 378,
      "reproductiveUrge": 3.559997,
      "hunger": 11.950027,
      "thirst": 24.310057,
      "speciesName": "",
      "xPos": 604.69183,
      "yPos": 30.349386,
      "currentState": 0,
      "genes": "4:500:1:98:23",
      "speed": 4,
      "eyeSght": 500,
      "gender": 1,
      "maxLife": 98,
      "reproductiveAge": 23
    },
    {
      "stamina": -17.170025,
      "age": 367,
      "reproductiveUrge": 3.4499972,
      "hunger": 4.1499977,
      "thirst": 9.51,
      "speciesName": "",
      "xPos": 214.1104,
      "yPos": 385.23172,
      "currentState": 0,
      "genes": "3:500:1:98:23",
      "speed": 3,
      "eyeSght": 500,
      "gender": 1,
      "maxLife": 98,
      "reproductiveAge": 23
    },
    {
      "stamina": -16.720032,
      "age": 358,
      "reproductiveUrge": 3.3599973,
      "hunger": 1.1,
      "thirst": 6.809996,
      "speciesName": "",
      "xPos": 100.02779,
      "yPos": 59.245644,
      "currentState": 0,
      "genes": "4:499:0:100:23",
      "speed": 4,
      "eyeSght": 499,
      "gender": 0,
      "maxLife": 100,
      "reproductiveAge": 23
    },
    {
      "stamina": -15.870043,
      "age": 341,
      "reproductiveUrge": 3.1799974,
      "hunger": 14.700038,
      "thirst": 29.910078,
      "speciesName": "",
      "xPos": 604.69293,
      "yPos": 30.348772,
      "currentState": 0,
      "genes": "4:499:1:98:24",
      "speed": 4,
      "eyeSght": 499,
      "gender": 1,
      "maxLife": 98,
      "reproductiveAge": 24
    },
    {
      "stamina": -15.820043,
      "age": 340,
      "reproductiveUrge": 3.1899974,
      "hunger": 13.650034,
      "thirst": 28.710073,
      "speciesName": "",
      "xPos": 604.7552,
      "yPos": 30.359459,
      "currentState": 0,
      "genes": "4:499:1:99:22",
      "speed": 4,
      "eyeSght": 499,
      "gender": 1,
      "maxLife": 99,
      "reproductiveAge": 22
    },
    {
      "stamina": -14.8900385,
      "age": 319,
      "reproductiveUrge": 2.9599977,
      "hunger": 15.910043,
      "thirst": 31.810085,
      "speciesName": "",
      "xPos": 684.4558,
      "yPos": 67.457344,
      "currentState": 0,
      "genes": "3:500:1:98:24",
      "speed": 3,
      "eyeSght": 500,
      "gender": 1,
      "maxLife": 98,
      "reproductiveAge": 24
    },
    {
      "stamina": -9.82002,
      "age": 220,
      "reproductiveUrge": 1.9799985,
      "hunger": 10.00002,
      "thirst": 20.11004,
      "speciesName": "",
      "xPos": 574.7262,
      "yPos": 28.92904,
      "currentState": 0,
      "genes": "5:499:0:99:23",
      "speed": 5,
      "eyeSght": 499,
      "gender": 0,
      "maxLife": 99,
      "reproductiveAge": 23
    },
    {
      "stamina": -8.3400135,
      "age": 188,
      "reproductiveUrge": 1.6699988,
      "hunger": 9.360018,
      "thirst": 18.710035,
      "speciesName": "",
      "xPos": 685.0949,
      "yPos": 68.166664,
      "currentState": 0,
      "genes": "3:498:0:98:22",
      "speed": 3,
      "eyeSght": 498,
      "gender": 0,
      "maxLife": 98,
      "reproductiveAge": 22
    },
    {
      "stamina": -6.840008,
      "age": 164,
      "reproductiveUrge": 1.419999,
      "hunger": 1.3599998,
      "thirst": 1.8000003,
      "speciesName": "",
      "xPos": 284.13492,
      "yPos": 338.5709,
      "currentState": 0,
      "genes": "3:498:1:99:23",
      "speed": 3,
      "eyeSght": 498,
      "gender": 1,
      "maxLife": 99,
      "reproductiveAge": 23
    },
    {
      "stamina": -5.670004,
      "age": 137,
      "reproductiveUrge": 1.1599993,
      "hunger": 3.4999979,
      "thirst": 8.109995,
      "speciesName": "",
      "xPos": 219.27077,
      "yPos": 384.63016,
      "currentState": 0,
      "genes": "3:497:0:98:22",
      "speed": 3,
      "eyeSght": 497,
      "gender": 0,
      "maxLife": 98,
      "reproductiveAge": 22
    },
    {
      "stamina": -2.489999,
      "age": 71,
      "reproductiveUrge": 0.4899998,
      "hunger": 3.5099978,
      "thirst": 7.0099955,
      "speciesName": "",
      "xPos": 264.17203,
      "yPos": 152.22433,
      "currentState": 0,
      "genes": "3:500:0:99:23",
      "speed": 3,
      "eyeSght": 500,
      "gender": 0,
      "maxLife": 99,
      "reproductiveAge": 23
    },
    {
      "stamina": -1.6899997,
      "age": 55,
      "reproductiveUrge": 0.32999995,
      "hunger": 2.7099986,
      "thirst": 5.409997,
      "speciesName": "",
      "xPos": 653.9034,
      "yPos": 55.00974,
      "currentState": 0,
      "genes": "4:499:1:97:23",
      "speed": 4,
      "eyeSght": 499,
      "gender": 1,
      "maxLife": 97,
      "reproductiveAge": 23
    },
    {
      "stamina": -0.5900002,
      "age": 33,
      "reproductiveUrge": 0.11999998,
      "hunger": 1.6099995,
      "thirst": 3.209999,
      "speciesName": "",
      "xPos": 292.3882,
      "yPos": 357.42587,
      "currentState": 0,
      "genes": "3:499:1:98:22",
      "speed": 3,
      "eyeSght": 499,
      "gender": 1,
      "maxLife": 98,
      "reproductiveAge": 22
    },
    {
      "stamina": 0.2599998,
      "age": 16,
      "reproductiveUrge": 0,
      "hunger": 0.7600001,
      "thirst": 1.5100002,
      "speciesName": "",
      "xPos": 276.42154,
      "yPos": 154.53864,
      "currentState": 0,
      "genes": "3:499:1:99:22",
      "speed": 3,
      "eyeSght": 499,
      "gender": 1,
      "maxLife": 99,
      "reproductiveAge": 22
    }
  ],
  "activeFood": [
    {
      "amountOfFood": 1,
      "speciesName": "",
      "xPos": 794,
      "yPos": 30
    },
    {
      "amountOfFood": 1,
      "speciesName": "",
      "xPos": 370,
      "yPos": 444
    },
    {
      "amountOfFood": 1,
      "speciesName": "",
      "xPos": 330,
      "yPos": 368
    },
    {
      "amountOfFood": 1,
      "speciesName": "",
      "xPos": 414,
      "yPos": 366
    },
    {
      "amountOfFood": 1,
      "speciesName": "",
      "xPos": 25,
      "yPos": 109
    },
    {
      "amountOfFood": 1,
      "speciesName": "",
      "xPos": 18,
      "yPos": 91
    },
    {
      "amountOfFood": 1,
      "speciesName": "",
      "xPos": 430,
      "yPos": 435
    },
    {
      "amountOfFood": 1,
      "speciesName": "",
      "xPos": 422,
      "yPos": 368
    },
    {
      "amountOfFood": 1,
      "speciesName": "",
      "xPos": 322,
      "yPos": 284
    },
    {
      "amountOfFood": 1,
      "speciesName": "",
      "xPos": 581,
      "yPos": 418
    },
    {
      "amountOfFood": 1,
      "speciesName": "",
      "xPos": 23,
      "yPos": 174
    },
    {
      "amountOfFood": 1,
      "speciesName": "",
      "xPos": 33,
      "yPos": 177
    },
    {
      "amountOfFood": 1,
      "speciesName": "",
      "xPos": 0,
      "yPos": 164
    },
    {
      "amountOfFood": 1,
      "speciesName": "",
      "xPos": 714,
      "yPos": 235
    },
    {
      "amountOfFood": 1,
      "speciesName": "",
      "xPos": 514,
      "yPos": 423
    },
    {
      "amountOfFood": 1,
      "speciesName": "",
      "xPos": 733,
      "yPos": 188
    },
    {
      "amountOfFood": 1,
      "speciesName": "",
      "xPos": 67,
      "yPos": 103
    },
    {
      "amountOfFood": 1,
      "speciesName": "",
      "xPos": 8,
      "yPos": 137
    },
    {
      "amountOfFood": 1,
      "speciesName": "",
      "xPos": 749,
      "yPos": 230
    },
    {
      "amountOfFood": 1,
      "speciesName": "",
      "xPos": 156,
      "yPos": 82
    },
    {
      "amountOfFood": 1,
      "speciesName": "",
      "xPos": 581,
      "yPos": 98
    },
    {
      "amountOfFood": 1,
      "speciesName": "",
      "xPos": 424,
      "yPos": 336
    },
    {
      "amountOfFood": 1,
      "speciesName": "",
      "xPos": 595,
      "yPos": 244
    },
    {
      "amountOfFood": 1,
      "speciesName": "",
      "xPos": 291,
      "yPos": 219
    },
    {
      "amountOfFood": 1,
      "speciesName": "",
      "xPos": 784,
      "yPos": 109
    },
    {
      "amountOfFood": 1,
      "speciesName": "",
      "xPos": 481,
      "yPos": 28
    },
    {
      "amountOfFood": 1,
      "speciesName": "",
      "xPos": 685,
      "yPos": 363
    },
    {
      "amountOfFood": 1,
      "speciesName": "",
      "xPos": 481,
      "yPos": 393
    },
    {
      "amountOfFood": 1,
      "speciesName": "",
      "xPos": 569,
      "yPos": 52
    },
    {
      "amountOfFood": 1,
      "speciesName": "",
      "xPos": 489,
      "yPos": 387
    },
    {
      "amountOfFood": 1,
      "speciesName": "",
      "xPos": 709,
      "yPos": 281
    },
    {
      "amountOfFood": 1,
      "speciesName": "",
      "xPos": 141,
      "yPos": 76
    },
    {
      "amountOfFood": 1,
      "speciesName": "",
      "xPos": 461,
      "yPos": 301
    },
    {
      "amountOfFood": 1,
      "speciesName": "",
      "xPos": 762,
      "yPos": 347
    },
    {
      "amountOfFood": 1,
      "speciesName": "",
      "xPos": 5,
      "yPos": 198
    },
    {
      "amountOfFood": 1,
      "speciesName": "",
      "xPos": 28,
      "yPos": 105
    },
    {
      "amountOfFood": 1,
      "speciesName": "",
      "xPos": 668,
      "yPos": 207
    },
    {
      "amountOfFood": 1,
      "speciesName": "",
      "xPos": 11,
      "yPos": 108
    },
    {
      "amountOfFood": 1,
      "speciesName": "",
      "xPos": 120,
      "yPos": 178
    },
    {
      "amountOfFood": 1,
      "speciesName": "",
      "xPos": 402,
      "yPos": 190
    },
    {
      "amountOfFood": 1,
      "speciesName": "",
      "xPos": 674,
      "yPos": 253
    },
    {
      "amountOfFood": 1,
      "speciesName": "",
      "xPos": 666,
      "yPos": 227
    },
    {
      "amountOfFood": 1,
      "speciesName": "",
      "xPos": 627,
      "yPos": 161
    },
    {
      "amountOfFood": 1,
      "speciesName": "",
      "xPos": 680,
      "yPos": 183
    },
    {
      "amountOfFood": 1,
      "speciesName": "",
      "xPos": 485,
      "yPos": 98
    },
    {
      "amountOfFood": 1,
      "speciesName": "",
      "xPos": 209,
      "yPos": 14
    }
  ],
  "activeWater": [
    {
      "amountOfWater": 1,
      "xPos": 83,
      "yPos": 66
    },
    {
      "amountOfWater": 1,
      "xPos": 582,
      "yPos": 426
    },
    {
      "amountOfWater": 1,
      "xPos": 594,
      "yPos": 408
    },
    {
      "amountOfWater": 1,
      "xPos": 544,
      "yPos": 32
    },
    {
      "amountOfWater": 1,
      "xPos": 442,
      "yPos": 193
    },
    {
      "amountOfWater": 1,
      "xPos": 96,
      "yPos": 378
    },
    {
      "amountOfWater": 1,
      "xPos": 166,
      "yPos": 197
    },
    {
      "amountOfWater": 1,
      "xPos": 609,
      "yPos": 242
    },
    {
      "amountOfWater": 1,
      "xPos": 108,
      "yPos": 360
    },
    {
      "amountOfWater": 1,
      "xPos": 182,
      "yPos": 231
    }
  ],
  "populationSizes": [
    10,
    10,
    10,
    10,
    10,
    10,
    10,
    10,
    10,
    10,
    10,
    10,
    10,
    10,
    10,
    10,
    10,
    10,
    10,
    10,
    10,
    10,
    10,
    10,
    10,
    10,
    10,
    10,
    10,
    10,
    10,
    10,
    10,
    10,
    10,
    10,
    10,
    10,
    10,
    10,
    10,
    10,
    10,
    10,
    10,
    10,
    10,
    10,
    10,
    10,
    10,
    10,
    10,
    10,
    10,
    10,
    10,
    10,
    10,
    10,
    10,
    10,
    10,
    10,
    10,
    10,
    10,
    10,
    10,
    10,
    10,
    10,
    10,
    10,
    10,
    10,
    10,
    10,
    10,
    10,
    10,
    10,
    10,
    10,
    10,
    10,
    10,
    10,
    10,
    10,
    10,
    10,
    10,
    10,
    10,
    10,
    10,
    10,
    10,
    10,
    10,
    10,
    10,
    10,
    10,
    10,
    10,
    10,
    10,
    10,
    10,
    10,
    10,
    10,
    10,
    10,
    10,
    10,
    10,
    10,
    10,
    10,
    10,
    10,
    10,
    10,
    10,
    10,
    10,
    10,
    10,
    10,
    10,
    10,
    10,
    10,
    10,
    10,
    10,
    10,
    10,
    10,
    10,
    10,
    10,
    10,
    10,
    10,
    10,
    10,
    10,
    10,
    10,
    10,
    10,
    10,
    10,
    10,
    10,
    10,
    10,
    10,
    10,
    10,
    10,
    10,
    10,
    10,
    10,
    10,
    10,
    10,
    10,
    10,
    10,
    10,
    10,
    10,
    10,
    10,
    10,
    10,
    10,
    10,
    10,
    10,
    10,
    10,
    10,
    10,
    10,
    10,
    10,
    10,
    10,
    10,
    10,
    10,
    10,
    10,
    10,
    10,
    10,
    10,
    10,
    10,
    10,
    10,
    10,
    10,
    10,
    10,
    10,
    10,
    10,
    10,
    10,
    10,
    10,
    10,
    10,
    10,
    10,
    10,
    10,
    10,
    10,
    10,
    10,
    10,
    10,
    10,
    10,
    10,
    10,
    10,
    10,
    10,
    10,
    10,
    10,
    10,
    10,
    10,
    10,
    10,
    10,
    10,
    10,
    10,
    10,
    10,
    10,
    10,
    10,
    10,
    10,
    10,
    10,
    10,
    10,
    10,
    10,
    10,
    10,
    10,
    11,
    11,
    11,
    11,
    11,
    11,
    11,
    11,
    11,
    11,
    11,
    11,
    11,
    11,
    11,
    11,
    11,
    11,
    11,
    11,
    11,
    11,
    11,
    11,
    11,
    11,
    11,
    11,
    11,
    11,
    11,
    11,
    11,
    11,
    11,
    11,
    11,
    11,
    11,
    11,
    11,
    11,
    11,
    11,
    11,
    11,
    11,
    11,
    11,
    11,
    11,
    11,
    11,
    11,
    11,
    11,
    11,
    11,
    11,
    11,
    11,
    11,
    11,
    11,
    11,
    11,
    11,
    11,
    11,
    11,
    11,
    11,
    11,
    11,
    11,
    11,
    11,
    11,
    11,
    11,
    11,
    11,
    11,
    11,
    11,
    11,
    11,
    11,
    11,
    11,
    11,
    11,
    11,
    11,
    11,
    11,
    11,
    11,
    11,
    11,
    11,
    11,
    11,
    11,
    11,
    11,
    11,
    11,
    11,
    11,
    11,
    11,
    11,
    11,
    11,
    11,
    11,
    11,
    11,
    11,
    11,
    11,
    11,
    11,
    11,
    11,
    11,
    11,
    11,
    11,
    11,
    11,
    11,
    11,
    11,
    11,
    11,
    11,
    11,
    11,
    11,
    11,
    11,
    11,
    11,
    11,
    11,
    11,
    11,
    11,
    11,
    11,
    11,
    11,
    11,
    11,
    11,
    11,
    11,
    11,
    11,
    11,
    11,
    11,
    11,
    11,
    11,
    11,
    11,
    11,
    11,
    11,
    11,
    11,
    11,
    11,
    11,
    11,
    11,
    11,
    11,
    11,
    11,
    11,
    11,
    11,
    11,
    11,
    11,
    11,
    11,
    11,
    11,
    11,
    11,
    11,
    11,
    11,
    11,
    11,
    11,
    11,
    11,
    11,
    11,
    11,
    11,
    11,
    11,
    11,
    11,
    11,
    11,
    11,
    11,
    11,
    11,
    11,
    11,
    11,
    11,
    11,
    11,
    11,
    11,
    11,
    11,
    11,
    11,
    11,
    11,
    11,
    11,
    11,
    11,
    11,
    11,
    11,
    11,
    11,
    11,
    11,
    11,
    11,
    11,
    11,
    11,
    11,
    11,
    11,
    11,
    11,
    11,
    11,
    11,
    11,
    11,
    11,
    11,
    11,
    11,
    11,
    11,
    11,
    11,
    11,
    11,
    11,
    11,
    11,
    11,
    11,
    11,
    11,
    11,
    11,
    11,
    11,
    11,
    11,
    11,
    11,
    11,
    11,
    12,
    12,
    12,
    12,
    12,
    12,
    12,
    12,
    12,
    12,
    12,
    12,
    12,
    12,
    12,
    12,
    12,
    12,
    12,
    12,
    12,
    12,
    12,
    12,
    12,
    12,
    12,
    12,
    12,
    12,
    12,
    12,
    12,
    12,
    12,
    12,
    12,
    12,
    12,
    12,
    12,
    12,
    12,
    12,
    12,
    12,
    12,
    12,
    12,
    12,
    12,
    12,
    12,
    12,
    12,
    12,
    12,
    12,
    12,
    12,
    12,
    12,
    12,
    12,
    12,
    12,
    13,
    13,
    13,
    13,
    13,
    13,
    13,
    13,
    13,
    13,
    13,
    13,
    13,
    13,
    13,
    13,
    13,
    13,
    13,
    13,
    13,
    13,
    13,
    13,
    13,
    13,
    13,
    13,
    13,
    13,
    13,
    13,
    13,
    13,
    13,
    13,
    13,
    13,
    13,
    13,
    13,
    13,
    13,
    13,
    13,
    13,
    13,
    13,
    13,
    13,
    13,
    13,
    13,
    13,
    13,
    13,
    13,
    13,
    13,
    13,
    13,
    13,
    13,
    13,
    13,
    13,
    13,
    13,
    13,
    13,
    13,
    13,
    13,
    13,
    13,
    13,
    13,
    13,
    13,
    13,
    13,
    13,
    13,
    13,
    13,
    13,
    13,
    13,
    13,
    13,
    13,
    13,
    13,
    13,
    13,
    13,
    13,
    13,
    13,
    13,
    13,
    13,
    13,
    13,
    13,
    13,
    13,
    13,
    13,
    13,
    13,
    13,
    13,
    13,
    13,
    13,
    13,
    13,
    13,
    13,
    13,
    13,
    13,
    13,
    13,
    13,
    13,
    13,
    13,
    13,
    13,
    13,
    13,
    13,
    13,
    13,
    13,
    13,
    13,
    13,
    14,
    14,
    14,
    14,
    14,
    14,
    14,
    14,
    14,
    14,
    14,
    14,
    14,
    14,
    14,
    14,
    14,
    14,
    14,
    14,
    14,
    14,
    14,
    14,
    14,
    14,
    14,
    14,
    14,
    14,
    14,
    14,
    14,
    14,
    14,
    14,
    14,
    14,
    14,
    14,
    14,
    14,
    14,
    14,
    14,
    14,
    14,
    14,
    14,
    14,
    14,
    14,
    14,
    14,
    14,
    14,
    14,
    14,
    14,
    14,
    14,
    14,
    14,
    14,
    14,
    14,
    14,
    14,
    14,
    14,
    14,
    14,
    14,
    14,
    14,
    14,
    14,
    14,
    14,
    14,
    14,
    14,
    14,
    14,
    14,
    14,
    14,
    14,
    14,
    14,
    14,
    14,
    14,
    14,
    14,
    14,
    14,
    14,
    14,
    14,
    14,
    14,
    15,
    15,
    15,
    15,
    15,
    15,
    15,
    15,
    15,
    15,
    15,
    15,
    15,
    15,
    15,
    15,
    15,
    15,
    15,
    15,
    15,
    15,
    16,
    16,
    16,
    16,
    16,
    16,
    16,
    16,
    16,
    16,
    16,
    16,
    16,
    16,
    16,
    16,
    16,
    17,
    17,
    17,
    17,
    17,
    17,
    17,
    17,
    17,
    17,
    17,
    17,
    17,
    17,
    17,
    17,
    17,
    17,
    17,
    17,
    17,
    17,
    17,
    17,
    17,
    17,
    17,
    17,
    17,
    17,
    17,
    17,
    17,
    17,
    17,
    17,
    17,
    17,
    17,
    18,
    18,
    18,
    18,
    18,
    18,
    18,
    18,
    18,
    18,
    18,
    18,
    18,
    18,
    18,
    18,
    18,
    18,
    18,
    18,
    18,
    18,
    18,
    18,
    18,
    18,
    18,
    18,
    18,
    18,
    18,
    18,
    18,
    18,
    18,
    18,
    18,
    18,
    18,
    18,
    18,
    18,
    18,
    18,
    18,
    18,
    18,
    18,
    18,
    18,
    18,
    18,
    18,
    18,
    18,
    18,
    18,
    18,
    18,
    18,
    18,
    18,
    18,
    18,
    18,
    19,
    19,
    19,
    19,
    19,
    19,
    19,
    19,
    19,
    19,
    19,
    19,
    19,
    19,
    19,
    19,
    19,
    19,
    19,
    19,
    19,
    19,
    19,
    19,
    19,
    19,
    19,
    19,
    19,
    19,
    19,
    19,
    19,
    19,
    19,
    19,
    19,
    19,
    19,
    19,
    19,
    19,
    19,
    19,
    19,
    19,
    19,
    19,
    19,
    19,
    19,
    19,
    19,
    19,
    19,
    19,
    18,
    18,
    18,
    18,
    19,
    19,
    19,
    19,
    19,
    19,
    19,
    19,
    19,
    19,
    19,
    20,
    20,
    20,
    20,
    20,
    20,
    20,
    20,
    20,
    21,
    21,
    21,
    21,
    21,
    21,
    21,
    21,
    21,
    21,
    21,
    21,
    21,
    21,
    21,
    21,
    21,
    22,
    23,
    23,
    23,
    23,
    23,
    23,
    23,
    23,
    23,
    23,
    23,
    23,
    23,
    23,
    23,
    23,
    23,
    23,
    23,
    23,
    23,
    24,
    24,
    24,
    24,
    24,
    24,
    24,
    24,
    24,
    24,
    24,
    24,
    24,
    24,
    24,
    24,
    24,
    24,
    24,
    24,
    24,
    24,
    24,
    24,
    24,
    24,
    24,
    24,
    24,
    24,
    24,
    24,
    24,
    24,
    24,
    24,
    24,
    24,
    24,
    24,
    24,
    24,
    24,
    24,
    24,
    24,
    24,
    24,
    24,
    24,
    24,
    24,
    24,
    24,
    24,
    24,
    24,
    24,
    24,
    24,
    24,
    24,
    24,
    24,
    24,
    24,
    24,
    24,
    24,
    24,
    24,
    24,
    24,
    24,
    24,
    24,
    24,
    24,
    24,
    24,
    24,
    24,
    24,
    24,
    24,
    24,
    24,
    24,
    24,
    24,
    24,
    24,
    24,
    24,
    24,
    24,
    24,
    24,
    24,
    25,
    25,
    25,
    25,
    25,
    25,
    25,
    25,
    25,
    25,
    25,
    25,
    25,
    25,
    25,
    25,
    25,
    25,
    25,
    25,
    25,
    25,
    25,
    25,
    25,
    25,
    25,
    25,
    25,
    25,
    25,
    25,
    26,
    26,
    26,
    26,
    26,
    26,
    26,
    26,
    26,
    26,
    26,
    26,
    26,
    26,
    26,
    26,
    26,
    26,
    26,
    26,
    26,
    26,
    26,
    26,
    27,
    27,
    27,
    27,
    27,
    27,
    27,
    27,
    27,
    27,
    27,
    27,
    27,
    27,
    27,
    27,
    27,
    27,
    27,
    27,
    27,
    27,
    27,
    27,
    27,
    27,
    27,
    28,
    28,
    28,
    28,
    28,
    28,
    28,
    28,
    28,
    28,
    28,
    28,
    28,
    28,
    28,
    28,
    28,
    28,
    28,
    28,
    28,
    28,
    28,
    28,
    28,
    28,
    28,
    28,
    28,
    28,
    28,
    28,
    28,
    28,
    28,
    28,
    28,
    28,
    28,
    28,
    28,
    28,
    28,
    28,
    28,
    28,
    28,
    28,
    28,
    28,
    28,
    28,
    28,
    28,
    28,
    28,
    28,
    28,
    28,
    28,
    28,
    28,
    28,
    28,
    28,
    28,
    29,
    29,
    29,
    29,
    29,
    29,
    29,
    29,
    29,
    29,
    29,
    29,
    29,
    29,
    29,
    29,
    30,
    30,
    30,
    30,
    30,
    30,
    30,
    30,
    30,
    30,
    30,
    30,
    30,
    30,
    30,
    30,
    30,
    30,
    30,
    30,
    30,
    30,
    31,
    31,
    31,
    31,
    31,
    31,
    31,
    31,
    31,
    31,
    31,
    31,
    31,
    31,
    31,
    31,
    31,
    32,
    32,
    32,
    32,
    32,
    32,
    32,
    32,
    32,
    32,
    32,
    32,
    32,
    32,
    32,
    32,
    32
  ],
  "foodSizes": [
    10,
    10,
    10,
    10,
    10,
    10,
    10,
    10,
    10,
    10,
    10,
    10,
    10,
    10,
    10,
    10,
    10,
    10,
    10,
    10,
    10,
    10,
    10,
    10,
    10,
    10,
    10,
    10,
    10,
    10,
    10,
    10,
    10,
    11,
    11,
    11,
    11,
    11,
    11,
    11,
    11,
    11,
    11,
    11,
    12,
    12,
    13,
    13,
    13,
    13,
    13,
    13,
    13,
    13,
    14,
    14,
    14,
    15,
    15,
    15,
    15,
    15,
    15,
    15,
    15,
    15,
    15,
    15,
    15,
    15,
    16,
    16,
    16,
    16,
    17,
    17,
    17,
    17,
    16,
    17,
    17,
    17,
    17,
    17,
    17,
    17,
    17,
    17,
    17,
    17,
    17,
    17,
    17,
    17,
    17,
    17,
    17,
    17,
    17,
    17,
    17,
    17,
    17,
    17,
    17,
    17,
    17,
    17,
    17,
    17,
    17,
    17,
    17,
    17,
    16,
    16,
    16,
    16,
    16,
    16,
    16,
    16,
    16,
    15,
    15,
    15,
    15,
    15,
    15,
    15,
    15,
    15,
    15,
    15,
    15,
    15,
    15,
    15,
    15,
    15,
    15,
    15,
    15,
    15,
    15,
    15,
    15,
    15,
    15,
    15,
    15,
    15,
    15,
    15,
    15,
    15,
    15,
    15,
    15,
    15,
    15,
    15,
    15,
    15,
    15,
    15,
    15,
    15,
    15,
    15,
    15,
    15,
    15,
    15,
    15,
    15,
    15,
    15,
    15,
    15,
    15,
    15,
    15,
    15,
    15,
    15,
    15,
    15,
    15,
    15,
    15,
    15,
    15,
    15,
    15,
    15,
    15,
    15,
    15,
    15,
    15,
    15,
    15,
    15,
    15,
    15,
    15,
    15,
    15,
    15,
    15,
    15,
    15,
    15,
    15,
    15,
    15,
    15,
    15,
    15,
    15,
    15,
    15,
    15,
    15,
    15,
    15,
    15,
    15,
    17,
    17,
    17,
    17,
    17,
    17,
    17,
    17,
    17,
    17,
    17,
    17,
    17,
    17,
    17,
    17,
    17,
    17,
    17,
    17,
    18,
    18,
    18,
    18,
    18,
    18,
    18,
    18,
    18,
    18,
    18,
    18,
    18,
    18,
    19,
    20,
    20,
    20,
    20,
    20,
    20,
    20,
    20,
    20,
    20,
    20,
    20,
    20,
    20,
    20,
    20,
    20,
    20,
    20,
    20,
    20,
    20,
    20,
    20,
    20,
    20,
    20,
    20,
    20,
    20,
    20,
    20,
    20,
    20,
    20,
    20,
    20,
    20,
    20,
    20,
    20,
    20,
    20,
    20,
    20,
    20,
    20,
    20,
    20,
    20,
    20,
    20,
    20,
    20,
    20,
    20,
    20,
    20,
    20,
    20,
    20,
    20,
    20,
    20,
    20,
    20,
    20,
    20,
    20,
    20,
    20,
    20,
    20,
    20,
    20,
    20,
    20,
    20,
    20,
    20,
    20,
    20,
    20,
    20,
    20,
    20,
    22,
    22,
    22,
    22,
    22,
    22,
    22,
    22,
    22,
    22,
    22,
    22,
    22,
    22,
    22,
    22,
    22,
    22,
    22,
    22,
    22,
    22,
    22,
    22,
    21,
    21,
    21,
    21,
    21,
    21,
    21,
    21,
    21,
    21,
    21,
    21,
    21,
    21,
    21,
    21,
    21,
    21,
    21,
    21,
    21,
    21,
    23,
    23,
    23,
    23,
    23,
    23,
    23,
    23,
    23,
    23,
    23,
    23,
    23,
    23,
    23,
    23,
    23,
    23,
    23,
    23,
    23,
    23,
    23,
    23,
    23,
    23,
    23,
    23,
    23,
    23,
    23,
    23,
    23,
    23,
    23,
    23,
    23,
    23,
    23,
    22,
    22,
    22,
    22,
    22,
    22,
    22,
    22,
    22,
    22,
    22,
    22,
    22,
    22,
    22,
    22,
    22,
    22,
    22,
    22,
    22,
    22,
    22,
    22,
    22,
    22,
    22,
    22,
    22,
    22,
    22,
    22,
    22,
    22,
    22,
    22,
    22,
    22,
    22,
    22,
    22,
    22,
    22,
    22,
    22,
    22,
    22,
    22,
    22,
    22,
    22,
    22,
    22,
    22,
    22,
    22,
    22,
    22,
    22,
    22,
    22,
    22,
    22,
    22,
    22,
    22,
    22,
    22,
    22,
    22,
    22,
    22,
    22,
    22,
    22,
    22,
    22,
    22,
    22,
    22,
    22,
    22,
    22,
    22,
    22,
    22,
    22,
    22,
    22,
    22,
    22,
    22,
    22,
    22,
    22,
    22,
    22,
    22,
    22,
    22,
    22,
    22,
    22,
    22,
    22,
    22,
    22,
    22,
    22,
    22,
    22,
    22,
    22,
    22,
    22,
    22,
    22,
    22,
    22,
    22,
    22,
    22,
    22,
    22,
    22,
    22,
    23,
    23,
    23,
    23,
    23,
    23,
    23,
    23,
    23,
    23,
    23,
    23,
    23,
    23,
    23,
    24,
    24,
    24,
    24,
    24,
    24,
    24,
    24,
    24,
    24,
    24,
    24,
    24,
    24,
    24,
    24,
    24,
    24,
    24,
    24,
    24,
    24,
    24,
    24,
    24,
    24,
    24,
    24,
    24,
    26,
    26,
    26,
    26,
    26,
    26,
    26,
    26,
    28,
    28,
    28,
    28,
    28,
    28,
    28,
    28,
    28,
    28,
    28,
    28,
    28,
    28,
    28,
    28,
    28,
    28,
    28,
    28,
    28,
    28,
    28,
    28,
    28,
    28,
    28,
    30,
    30,
    30,
    30,
    30,
    30,
    30,
    30,
    30,
    30,
    30,
    30,
    30,
    30,
    30,
    30,
    30,
    30,
    30,
    30,
    30,
    30,
    30,
    30,
    30,
    30,
    30,
    31,
    31,
    31,
    31,
    31,
    31,
    31,
    31,
    31,
    31,
    31,
    31,
    31,
    31,
    31,
    31,
    31,
    31,
    31,
    31,
    31,
    31,
    31,
    31,
    31,
    31,
    31,
    31,
    31,
    31,
    31,
    31,
    31,
    31,
    31,
    31,
    31,
    31,
    31,
    31,
    31,
    31,
    31,
    31,
    31,
    31,
    31,
    31,
    31,
    31,
    31,
    31,
    31,
    31,
    31,
    31,
    31,
    31,
    31,
    32,
    32,
    32,
    32,
    32,
    32,
    32,
    32,
    32,
    32,
    32,
    32,
    32,
    32,
    32,
    32,
    32,
    32,
    32,
    32,
    32,
    31,
    31,
    31,
    31,
    31,
    31,
    31,
    31,
    31,
    31,
    31,
    31,
    31,
    31,
    31,
    31,
    31,
    31,
    31,
    31,
    31,
    31,
    31,
    31,
    31,
    31,
    31,
    31,
    31,
    31,
    31,
    31,
    31,
    31,
    31,
    31,
    31,
    31,
    31,
    31,
    31,
    31,
    31,
    31,
    31,
    31,
    31,
    31,
    31,
    31,
    31,
    31,
    31,
    31,
    31,
    31,
    30,
    30,
    30,
    30,
    30,
    30,
    30,
    30,
    30,
    30,
    30,
    30,
    30,
    30,
    30,
    30,
    30,
    30,
    30,
    30,
    30,
    30,
    30,
    30,
    30,
    30,
    30,
    30,
    30,
    30,
    30,
    30,
    30,
    30,
    30,
    30,
    30,
    30,
    30,
    30,
    30,
    30,
    30,
    30,
    30,
    30,
    30,
    30,
    30,
    30,
    30,
    30,
    30,
    29,
    29,
    29,
    29,
    29,
    29,
    29,
    29,
    29,
    29,
    29,
    29,
    29,
    29,
    29,
    29,
    29,
    30,
    30,
    30,
    30,
    30,
    30,
    30,
    30,
    30,
    30,
    30,
    30,
    30,
    30,
    30,
    30,
    30,
    30,
    30,
    30,
    30,
    30,
    30,
    29,
    29,
    29,
    29,
    29,
    29,
    29,
    29,
    29,
    29,
    30,
    30,
    30,
    30,
    30,
    30,
    30,
    30,
    30,
    30,
    29,
    29,
    29,
    29,
    29,
    29,
    29,
    29,
    29,
    29,
    29,
    29,
    29,
    29,
    29,
    29,
    29,
    29,
    29,
    29,
    29,
    29,
    29,
    29,
    29,
    29,
    29,
    30,
    30,
    30,
    30,
    29,
    29,
    29,
    29,
    29,
    29,
    29,
    29,
    29,
    29,
    29,
    29,
    29,
    29,
    29,
    29,
    28,
    28,
    28,
    28,
    28,
    29,
    29,
    29,
    29,
    29,
    29,
    29,
    29,
    29,
    29,
    29,
    29,
    29,
    29,
    29,
    29,
    29,
    29,
    29,
    29,
    29,
    29,
    29,
    29,
    29,
    29,
    30,
    30,
    30,
    30,
    30,
    30,
    30,
    30,
    30,
    30,
    30,
    30,
    30,
    30,
    30,
    30,
    30,
    30,
    30,
    30,
    30,
    31,
    31,
    31,
    31,
    31,
    31,
    31,
    31,
    31,
    31,
    31,
    31,
    31,
    31,
    31,
    31,
    31,
    31,
    31,
    31,
    31,
    31,
    31,
    31,
    31,
    31,
    31,
    31,
    31,
    31,
    31,
    31,
    31,
    31,
    31,
    31,
    31,
    31,
    30,
    30,
    30,
    30,
    30,
    30,
    30,
    30,
    30,
    30,
    30,
    30,
    30,
    30,
    31,
    31,
    31,
    31,
    31,
    31,
    31,
    31,
    31,
    31,
    31,
    31,
    31,
    33,
    33,
    33,
    33,
    33,
    33,
    34,
    34,
    34,
    34,
    34,
    34,
    34,
    34,
    34,
    34,
    34,
    34,
    34,
    34,
    34,
    34,
    34,
    34,
    34,
    34,
    34,
    33,
    33,
    33,
    35,
    35,
    35,
    35,
    35,
    35,
    35,
    35,
    37,
    37,
    37,
    37,
    37,
    37,
    37,
    37,
    37,
    37,
    37,
    37,
    37,
    37,
    37,
    38,
    38,
    38,
    38,
    38,
    38,
    38,
    38,
    38,
    37,
    37,
    36,
    36,
    36,
    36,
    36,
    36,
    36,
    36,
    36,
    36,
    36,
    36,
    36,
    36,
    36,
    36,
    36,
    36,
    36,
    36,
    36,
    37,
    37,
    37,
    37,
    37,
    37,
    37,
    37,
    37,
    37,
    37,
    37,
    37,
    37,
    37,
    37,
    37,
    37,
    37,
    37,
    37,
    37,
    37,
    37,
    36,
    36,
    36,
    37,
    37,
    37,
    37,
    37,
    37,
    37,
    37,
    38,
    38,
    38,
    38,
    38,
    38,
    38,
    38,
    38,
    38,
    38,
    38,
    38,
    38,
    38,
    38,
    38,
    38,
    38,
    38,
    38,
    38,
    38,
    37,
    37,
    37,
    37,
    37,
    37,
    37,
    37,
    37,
    37,
    37,
    37,
    37,
    37,
    37,
    37,
    37,
    36,
    36,
    36,
    36,
    36,
    36,
    36,
    36,
    36,
    36,
    36,
    36,
    36,
    36,
    36,
    37,
    37,
    37,
    37,
    37,
    37,
    36,
    35,
    35,
    35,
    35,
    35,
    35,
    36,
    36,
    36,
    36,
    36,
    36,
    36,
    36,
    37,
    37,
    37,
    37,
    37,
    37,
    37,
    37,
    36,
    36,
    37,
    37,
    37,
    37,
    37,
    37,
    37,
    37,
    37,
    37,
    37,
    37,
    37,
    37,
    37,
    39,
    39,
    39,
    39,
    39,
    39,
    39,
    39,
    39,
    39,
    39,
    39,
    39,
    39,
    39,
    38,
    38,
    38,
    38,
    39,
    39,
    39,
    39,
    39,
    39,
    39,
    39,
    39,
    39,
    39,
    39,
    39,
    39,
    39,
    39,
    39,
    39,
    39,
    39,
    39,
    39,
    39,
    39,
    39,
    39,
    39,
    39,
    39,
    38,
    38,
    38,
    38,
    38,
    38,
    39,
    39,
    39,
    39,
    39,
    39,
    39,
    39,
    39,
    39,
    39,
    39,
    39,
    41,
    41,
    42,
    42,
    42,
    42,
    42,
    42,
    42,
    42,
    42,
    42,
    42,
    42,
    42,
    42,
    42,
    42,
    42,
    42,
    42,
    42,
    42,
    42,
    42,
    42,
    42,
    42,
    42,
    43,
    43,
    43,
    43,
    43,
    43,
    43,
    43,
    43,
    43,
    43,
    43,
    43,
    44,
    44,
    44,
    44,
    44,
    44,
    45,
    45,
    45,
    45,
    45,
    45,
    45,
    45,
    45,
    45,
    45,
    45,
    45,
    46,
    46,
    46,
    46,
    46,
    46,
    46,
    46,
    46,
    46,
    46
  ]
}